pypi_test_ameynert/__init__.py
pypi_test_ameynert/main.py
pypi_test_ameynert/py.typed
pypi_test_ameynert/tools/__init__.py
pypi_test_ameynert/tools/hello.py
pypi_test_ameynert-0.1.0.dist-info/LICENSE
pypi_test_ameynert-0.1.0.dist-info/METADATA
pypi_test_ameynert-0.1.0.dist-info/WHEEL
pypi_test_ameynert-0.1.0.dist-info/entry_points.txt
pypi_test_ameynert-0.1.0.dist-info/RECORD
