Metadata-Version: 2.3
Name: pypi_test_ameynert
Version: 0.1.0
Summary: ...
License: MIT
Author: Fulcrum Genomics LLC
Author-email: contact@fulcrumgenomics.com
Requires-Python: >=3.11.0,<4.0
Classifier: Development Status :: 3 - Alpha
Classifier: License :: OSI Approved :: MIT License
Classifier: Programming Language :: Python :: 3
Classifier: Programming Language :: Python :: 3.11
Classifier: Programming Language :: Python :: 3.12
Classifier: Programming Language :: Python :: 3.13
Requires-Dist: defopt (>=6.4.0,<7.0.0)
Project-URL: Bug Tracker, https://github.com/ameynert/pypi_test_ameynert/issues
Project-URL: Documentation, https://github.com/ameynert/pypi_test_ameynert
Project-URL: Homepage, https://github.com/ameynert/pypi_test_ameynert
Project-URL: Repository, https://github.com/ameynert/pypi_test_ameynert
